ga_extractor/__init__.py
ga_extractor/__main__.py
ga_extractor/extractor.py
ga_extractor-0.1.1.dist-info/entry_points.txt
ga_extractor-0.1.1.dist-info/LICENSE
ga_extractor-0.1.1.dist-info/WHEEL
ga_extractor-0.1.1.dist-info/METADATA
ga_extractor-0.1.1.dist-info/RECORD
